doc/conf.py
py3dtools/__init__.py
py3dtools/mirrorobj/__init__.py
py3dtools/mirrorobj/mirrorobj.py
py3dtools/stl2obj/__init__.py
py3dtools/stl2obj/stl2obj.py
py3dtools/vtp2stl/__init__.py
py3dtools/vtp2stl/vtp2stl.py
test/test.py
py3dtools_risingsunz-0.0.4.dist-info/LICENSE
py3dtools_risingsunz-0.0.4.dist-info/METADATA
py3dtools_risingsunz-0.0.4.dist-info/WHEEL
py3dtools_risingsunz-0.0.4.dist-info/entry_points.txt
py3dtools_risingsunz-0.0.4.dist-info/top_level.txt
py3dtools_risingsunz-0.0.4.dist-info/RECORD
